[{"time":"01:51","quoteFirst":"“Fogo Island and ","quoteTime":"one fifty-one A. M.","quoteLast":",” announced Ned laughing.","title":"The Airship Boys' Ocean Flyer; Or, New York to London in Twelve Hours","author":"Sayler, H. L. (Harry Lincoln), 1863-1913; Riesenberg, Sidney H., 1885-1971 [Illustrator]","gutenbergReference":"49416","hash":"530e9a1d947c08a930ca81176dbf4a7d6932ed5808b2a1c4cc491c0dc6fc1c73"},{"time":"01:51","quoteFirst":"I've done a double trick: on the wagon day times, night cashier in a drug store from ","quoteTime":"nine till two a.m.","quoteLast":" I've cut out theaters, cigarettes, and drinks.","title":"Odd Numbers\nBeing Further Chronicles of Shorty McCabe","author":"Ford, Sewell, 1868-1946","gutenbergReference":"26528","hash":"9c7a6ef25880712512184320c4b3b4ca5227ae51838f0d6ad1532986b643b309"}]