[
  {
    "time": "08:29",
    "quoteFirst": "",
    "quoteTime": "8:29 A.M.",
    "quoteLast": "",
    "title": "Syndrome",
    "author": "Hoover, Thomas, 1941-",
    "gutenbergReference": "34321",
    "matchType": 2,
    "hash": "7bc145608c224fa3cd74aa628647d4f39e2e60861d04566fb4cac33889f1d262"
  },
  {
    "time": "08:29",
    "quoteFirst": "Orders to detrain were given at ",
    "quoteTime": "8:29 a. m.",
    "quoteLast": " Tired and hungry the soldiers were greeted on the pier by a large delegation of Red Cross workers who had steaming hot coffee, delicious buns, cigarettes and candy to distribute to the regiment as a farewell tribute and morning appetizer.",
    "title": "The Delta of the Triple Elevens",
    "author": "Bachman, William Elmer, 1894-1966",
    "gutenbergReference": "20468",
    "matchType": 2,
    "hash": "aa28a00c7caf103b7d3e455c060941bda207b96b31a423ed4d035e70c70f6dfd"
  }
]