[
  {
    "time": "10:40",
    "quoteFirst": "It was ",
    "quoteTime": "twenty minutes to eleven",
    "quoteLast": ". Leaning against the lamp-post, his eyes fixed on the long hand of his watch, he counted impatiently the minutes which had yet to pass. At eleven o'clock precisely Hermann walked up the steps, pushed open the street door, and went into the vestibule, which was well lighted.",
    "title": "The Queen of Spades, and other stories",
    "author": "Pushkin, Aleksandr Sergeevich, 1799-1837; Edwards, H. Sutherland, Mrs. [Translator]",
    "gutenbergReference": "55024",
    "matchType": 1,
    "hash": "8a0347b6c0a541a4223839b4281c5f2e64d73868fb3c8707cd0532723f54afff"
  },
  {
    "time": "10:40",
    "quoteFirst": "“Why, this is the Thursday my nepher in Rockford gits married. An’ to git there in time fur the weddin’ we’ve got to catch the eleven o’clock train. So hurry, now, as it’s ",
    "quoteTime": "twenty minutes to eleven",
    "quoteLast": " already.”",
    "title": "Poppy Ott's pedigreed pickles",
    "author": "Edwards, Leo, 1884-1944; Salg, Bert, 1881-1938 [Illustrator]",
    "gutenbergReference": "71240",
    "matchType": 1,
    "hash": "9f559dcb0e357ae0184def40b945650cc17903908aaff9a3b1037bfc4bb5fc4b"
  },
  {
    "time": "10:40",
    "quoteFirst": "It wanted some ",
    "quoteTime": "twenty minutes to eleven",
    "quoteLast": " when the \"brougham with celluloid fittings,\" containing Miss Hancock, drove up the drive and stopped before \"The Laurels.\"",
    "title": "Fanny Lambert: A Novel",
    "author": "Stacpoole, H. De Vere (Henry De Vere), 1863-1951",
    "gutenbergReference": "55454",
    "matchType": 1,
    "hash": "b5e3100e076d7560df6e9cf9876b4a44327a4e7890aaf06936da8f654a2321c4"
  },
  {
    "time": "10:40",
    "quoteFirst": "\"I must go to bed,\" said Grace, breaking the significant silence that had fallen on the quartette. \"Come, Anne, it's ",
    "quoteTime": "twenty minutes to eleven",
    "quoteLast": ".",
    "title": "Grace Harlowe's Third Year at Overton College",
    "author": "Chase, Josephine, -1931",
    "gutenbergReference": "20473",
    "matchType": 1,
    "hash": "e040eb2630d885def1a0c9cc67201c68dba0fede61227c8ace6c3c90b7368e92"
  },
  {
    "time": "10:40",
    "quoteFirst": "Punctually at ",
    "quoteTime": "twenty minutes to eleven",
    "quoteLast": " on Sunday mornings the fifty-six pupils and the seven mistresses would leave the great gate of the Villa Camellia and march into the town, along the esplanade under the grove of palm trees, then through the beautiful sheltered garden of the Hôtel Anglais, where many exotic flowers and shrubs were blooming and the white arum lilies were like an Easter festival, to the doorway, under the jessamine-covered veranda, that led to the _Eglise anglaise et américaine_.",
    "title": "The Jolliest School of All",
    "author": "Brazil, Angela, 1869-1947",
    "gutenbergReference": "20163",
    "matchType": 1,
    "hash": "98f9c8b018b7de2d5a4cbe09260ca36adf4de792a04c6f0b60d176a76743eb14"
  },
  {
    "time": "10:40",
    "quoteFirst": "At ",
    "quoteTime": "forty minutes past ten",
    "quoteLast": " the signal was made to form line of battle ahead and astern of the Victory, and to steer S.S.W. The fog was now cleared off, and the British fleet were seen admirably formed in the closest order; while the Spaniards were stretching in two straggling bodies across the horizon, leaving an open space between.",
    "title": "Blackwood's Edinburgh Magazine — Volume 55, No. 342, April, 1844",
    "author": "Various",
    "gutenbergReference": "13633",
    "matchType": 1,
    "hash": "58944de6f3312bc3cd40cdf25560f2c050fd4448e7567622ae6ddf9af47105c5"
  },
  {
    "time": "10:40",
    "quoteFirst": "Time, ",
    "quoteTime": "10.40 A.M.",
    "quoteLast": "",
    "title": "The Catalpa Expedition",
    "author": "Pease, Zeph. W. (Zephaniah Walter), 1861-1933",
    "gutenbergReference": "62633",
    "matchType": 2,
    "hash": "a191e68f52b6141c184ce4718d1cc76485bdd4d82919e1e9b2ca8bd636c51e9e"
  },
  {
    "time": "10:40",
    "quoteFirst": "Jewell's Wharf, Brooklyn, at ",
    "quoteTime": "10.40 A.M.",
    "quoteLast": "",
    "title": "How to Travel\r\nHints, Advice, and Suggestions to Travelers by Land and Sea all over the Globe.",
    "author": "Knox, Thomas Wallace, 1835-1896",
    "gutenbergReference": "45162",
    "matchType": 2,
    "hash": "b878a70694fc379beee91a785462dce289a475d45275db5d9052481c648b176c"
  },
  {
    "time": "10:40",
    "quoteFirst": "Time, ",
    "quoteTime": "10.40 A.M.",
    "quoteLast": "",
    "title": "The Catalpa Expedition",
    "author": "Pease, Zeph. W. (Zephaniah Walter), 1861-1933",
    "gutenbergReference": "62633",
    "matchType": 2,
    "hash": "a191e68f52b6141c184ce4718d1cc76485bdd4d82919e1e9b2ca8bd636c51e9e"
  },
  {
    "time": "10:40",
    "quoteFirst": "18 Bombardment from ",
    "quoteTime": "10:40 A. M.",
    "quoteLast": "; some victims.",
    "title": "The Bombardment of Reims",
    "author": "Ferree, Barr, 1862-1924",
    "gutenbergReference": "49649",
    "matchType": 2,
    "hash": "d12c4ad66c5ac1b646bfc8e86bc95d8ce7505ff5d051186a7ba9bac8b68f1f42"
  },
  {
    "time": "10:40",
    "quoteFirst": "\"Well, you'll need it,\" said Carlton, grimly.  \"This is going to be a long trip.  It is ",
    "quoteTime": "twenty minutes to eleven",
    "quoteLast": " now; you will have to hurry.",
    "title": "The Princess Aline",
    "author": "Davis, Richard Harding, 1864-1916",
    "gutenbergReference": "327",
    "matchType": 1,
    "hash": "1135c14037c26a537500e051fec8f279b8867a49781acbed429a8fe84427fc20"
  },
  {
    "time": "10:40",
    "quoteFirst": "\"It must be late,\" said he. \"En vérité, it is ",
    "quoteTime": "twenty minutes to eleven",
    "quoteLast": "! I should not have thought it.\"",
    "title": "To Leeward",
    "author": "Crawford, F. Marion (Francis Marion), 1854-1909",
    "gutenbergReference": "40181",
    "matchType": 1,
    "hash": "1125ff5b2cfcfc8a3834655e13a067150966f26b05945747eab1439dd5b7e67e"
  },
  {
    "time": "10:40",
    "quoteFirst": "Dick drove into Bathgate at ",
    "quoteTime": "twenty minutes to eleven",
    "quoteLast": ". He always liked to give himself plenty of time to catch a train, but hated waiting about on the platform. So he stopped at the George Hotel and went into the hall for a whisky-and-soda.",
    "title": "The Squire's Daughter: Being the First Book in the Chronicles of the Clintons",
    "author": "Marshall, Archibald, 1866-1934",
    "gutenbergReference": "31381",
    "matchType": 1,
    "hash": "c14a75b847e60229137dd4a0e5484bc599ab674a335a271e5276fd6b925e56ed"
  },
  {
    "time": "10:40",
    "quoteFirst": "\"The Assistant Commissioner told me to take charge of the inquiry without delay, sir,\" explained Winter. He glanced at his watch. \"We have not been long on the road. It is only ",
    "quoteTime": "twenty minutes to eleven",
    "quoteLast": ".\"",
    "title": "The Strange Case of Mortimer Fenley",
    "author": "Tracy, Louis, 1863-1928",
    "gutenbergReference": "26447",
    "matchType": 1,
    "hash": "065103a6a0adabce954b37593b7412b9479b79beca48fad1b63ae6f645cbe673"
  },
  {
    "time": "10:40",
    "quoteFirst": "\"Now, it is known,\" added Mr. Mitchell, \"from the testimony of a boatman, whose boat passed Camden Bridge at ",
    "quoteTime": "forty minutes past ten",
    "quoteLast": " in the evening, that the bridge was closed according to regulation, after his passage.\"",
    "title": "In Search of the Castaways\nA Romantic Narrative of the Loss of Captain Grant of the Brig Britannia and of the Adventures of His Children and Friends in His Discovery and Rescue",
    "author": "Verne, Jules, 1828-1905",
    "gutenbergReference": "46597",
    "matchType": 1,
    "hash": "6ff4c78034b3afab4eba7bcf711ccdd3a26b5473fc1107d0720b6775d8a63a8c"
  },
  {
    "time": "10:40",
    "quoteFirst": "All present felt, as he retired, that the end of the Rebellion had come.  At ",
    "quoteTime": "10.40 A. M.",
    "quoteLast": " Lee reported further: \"I see no prospect of doing more than holding our position here till night.  I am not certain that I can do that.",
    "title": "The Great Conspiracy, Complete",
    "author": "Logan, John Alexander, 1826-1886",
    "gutenbergReference": "7140",
    "matchType": 2,
    "hash": "93c6638fbf15557c7e4dd7a03496c4af2cfa73c4017e1d909e3e91666bc2f9d2"
  },
  {
    "time": "10:40",
    "quoteFirst": "One of our horses having strayed, we did not start till ",
    "quoteTime": "10.40 a.m.",
    "quoteLast": ", when we steered in about a South-East direction for eight miles, and camped on an elevated grassy spot, called Mingan, with water in the granite rocks, probably permanent. The thickets were a little less dense than usual, but without any grass, except at the spots mentioned.",
    "title": "Explorations in Australia\r\n1.-Explorations in search of Dr. Leichardt and party. 2.-From Perth to Adelaide, around the great Australian bight. 3.-From Champion Bay, across the desert to the telegraph and to Adelaide. With an appendix on the condition of Western Australia.",
    "author": "Forrest, John Forrest, Baron, 1847-1918",
    "gutenbergReference": "9958",
    "matchType": 2,
    "hash": "3c720ca3ed005e75bb7834ebae9e358dea09aaa50addf7c130d5bf1328dc0726"
  },
  {
    "time": "10:40",
    "quoteFirst": "A good performance in long distance railway running was established by the Great Western Railway Company in connection with the visit in 1903 of the Prince and Princess of Wales to Cornwall. Their Royal Highnesses left Paddington in a special division of the Cornishman at ",
    "quoteTime": "10.40 a.m.",
    "quoteLast": ", the train being timed to do the non-stop run to North Road, Plymouth, a distance of 245 miles, in four hours and a half. This time was, however, reduced to the extent of 36-1/4 min.",
    "title": "The King's Post\r\nBeing a volume of historical facts relating to the posts, mail coaches, coach roads, and railway mail services of and connected with the ancient city of Bristol from 1580 to the present time",
    "author": "Tombs, Robert Charles, 1842-1923",
    "gutenbergReference": "28533",
    "matchType": 2,
    "hash": "5d06cc43cad95e8679cde9dd4ca290b5f665f8e2191b1e5563e2147599527e55"
  },
  {
    "time": "10:40",
    "quoteFirst": "On June 7 the temperature was 103.7°F. and the sheep still refused to eat. On the 8th the temperature was 103.2°F. at ",
    "quoteTime": "10.40 a.m.",
    "quoteLast": ", and the stools were still numerous and soft.",
    "title": "Barium: A Cause of the Loco-Weed Disease",
    "author": "Crawford, Albert Cornelius",
    "gutenbergReference": "40256",
    "matchType": 2,
    "hash": "20bfbc263d44bbcfefa80babb08b17e4ec11fb28eddf9be7b41eb040a74c05b3"
  },
  {
    "time": "10:40",
    "quoteFirst": "Fig. 185. Lilium auratum: apogeotropic movement of stem, traced on a vertical glass during 2 days and 2 nights, from ",
    "quoteTime": "10.40 A.M.",
    "quoteLast": " March 18th to 8 A.M. 20th. Figure reduced to one-half of the original scale.",
    "title": "The Power of Movement in Plants",
    "author": "Darwin, Charles, 1809-1882; Darwin, Francis, Sir, 1848-1925",
    "gutenbergReference": "5605",
    "matchType": 2,
    "hash": "499f03134184b71da26842b95b54f8dc7810e2627823616ae289e9a4528c8437"
  }
]