[
  {
    "time": "14:15",
    "quoteFirst": "\"I know,\" she said meekly. \"It's all my fault. I never told you. I've asked the Bishop of Frome to lunch, and I can't turn him out at a ",
    "quoteTime": "quarter-past two",
    "quoteLast": ", can I? What date is there free?\"",
    "title": "The Fortunate Youth",
    "author": "Locke, William John, 1863-1930",
    "gutenbergReference": "4379",
    "matchType": 1,
    "hash": "352b0b54e68801458a167543507c41508a807a9c9e8e2b90a266816efa0eda9b"
  },
  {
    "time": "14:15",
    "quoteFirst": "St. Michael's chimed the ",
    "quoteTime": "quarter after two",
    "quoteLast": " and sleep, long absent, was coming at last when, suddenly, the sound of a light footstep on the piazza drove her leagues away.",
    "title": "The Ghost Girl",
    "author": "Stacpoole, H. De Vere (Henry De Vere), 1863-1951",
    "gutenbergReference": "26986",
    "matchType": 1,
    "hash": "3c93e1bc9b45afb6cfa6600f03b46b3245098e6d97404b29e3cf3c2110383e9b"
  },
  {
    "time": "14:15",
    "quoteFirst": "; crossed the Roanoke river; at 2 P. M. halted for dinner; at 5 fell in and moved forward; halted at 6:30, and camped for the night (marched twenty miles). 5th, marched at 5:30 A. M.; at ",
    "quoteTime": "2:15 P. M.",
    "quoteLast": " halted for dinner; marched at 4; halted at 6:30 and camped for the night (marched twenty miles). 6th, marched at 5 A. M.; halted at 10:45 for dinner; fell in at 1 P. M.",
    "title": "Journal History of the Twenty-Ninth Ohio Veteran Volunteers, 1861-1865\r\nIts Victories and its Reverses. And the campaigns and battles of Winchester, Port Republic, Cedar Mountain, Chancellorsville, Gettysburg, Lookout Mountain, Atlanta, the March to the Sea, and the campaign of the Carolinas, in which it bore an honorable part",
    "author": "SeCheverell, J. Hamp (John Hamilton)",
    "gutenbergReference": "65589",
    "matchType": 2,
    "hash": "cb0a298da3587ed487904f5fee214c4bdd9dbe29a61c7203176e3e8178da2c6e"
  },
  {
    "time": "14:15",
    "quoteFirst": "The church clock is chiming a ",
    "quoteTime": "quarter-past two",
    "quoteLast": ", Near the \"Lion\"!",
    "title": "The Lazy Minstrel",
    "author": "Ashby-Sterry, J. (Joseph), -1917",
    "gutenbergReference": "42915",
    "matchType": 1,
    "hash": "acc461de93c17d4540b246d3b578b1a5cfcf5d41b191375d9eecd662dee39d9e"
  },
  {
    "time": "14:15",
    "quoteFirst": "The answer to this question came later on in the day. She was walking back to school at a ",
    "quoteTime": "quarter past two that afternoon",
    "quoteLast": ", when just by the windmill she met Morland himself on a motor bicycle. He dismounted at once.",
    "title": "The Head Girl at the Gables",
    "author": "Brazil, Angela, 1869-1947; Salmon, Balliol, 1868-1953 [Illustrator]",
    "gutenbergReference": "32575",
    "matchType": 0,
    "hash": "86ccfd63d883d9bb2b5d37c06a899814ab79534860d6aeabd9979fe8c4e09e74"
  },
  {
    "time": "14:15",
    "quoteFirst": "On the other bank a small and almost vertical railroad, worked by a rope on the American side, hoisted us to the top. At half-past one we took the express, which put us down at Buffalo at a ",
    "quoteTime": "quarter past two",
    "quoteLast": ". After visiting this large new town, and tasting the water of Lake Erie, we again took the New York Central Railway at six o’clock in the evening. The next day, on leaving the comfortable beds of a “sleeping car,” we found ourselves at Albany, and the Hudson Railroad, which runs along the left bank of the river, brought us to New York a few hours later.",
    "title": "A Floating City, and The Blockade Runners",
    "author": "Verne, Jules, 1828-1905",
    "gutenbergReference": "67829",
    "matchType": 1,
    "hash": "976043d532b28756f96acb0f55381848cb1318204b5b639ae1b05750192d84dc"
  },
  {
    "time": "14:15",
    "quoteFirst": "Magpie needs some exercise, and I want to ask how an old friend of mine is, who lives too far off to walk there; though her house too is on the edge of the forest.  That will take us about an hour and a half, so if we start at a ",
    "quoteTime": "quarter past two",
    "quoteLast": " we shall still have time for a wander on this side of the woods before it gets too chilly and dusk.\"",
    "title": "The Wood-Pigeons and Mary",
    "author": "Molesworth, Mrs., 1839-1921; Millar, H. R. (Harold Robert), 1869-1942 [Illustrator]",
    "gutenbergReference": "43107",
    "matchType": 1,
    "hash": "65ac9bbc4a30b31fb836382af7c14bf63082f441b15be2b173290af478ae53b5"
  },
  {
    "time": "14:15",
    "quoteFirst": "At a ",
    "quoteTime": "quarter past two",
    "quoteLast": " on this eventful day, the 30th of May 1860, Garibaldi and the Neapolitan generals, Letizia and Chretien, stepped on board the flag-ship _Hannibal_ which Admiral Mundy offered as neutral ground for their meeting. Curiously enough, both parties, reaching the mole simultaneously, were rowed out in the same ship's boat, which was waiting in readiness.",
    "title": "The Liberation of Italy, 1815-1870",
    "author": "Martinengo-Cesaresco, Evelyn Lilian Hazeldine Carrington, contessa, 1852-1931",
    "gutenbergReference": "14078",
    "matchType": 1,
    "hash": "0200076b81e687cf87aecc0b55a1c1e40b74e403575e64337a6eade5800dd039"
  },
  {
    "time": "14:15",
    "quoteFirst": "After lunch Millicent went to her desk, and in a fit of caprice wrote a letter. She read it, and started to tear it up. Then she changed her mind, and left it, sealed, on her desk. It was a ",
    "quoteTime": "quarter past two",
    "quoteLast": ".",
    "title": "The Yale Literary Magazine (Vol. LXXXIX, No. 1, 1923)",
    "author": "Various",
    "gutenbergReference": "69966",
    "matchType": 1,
    "hash": "5174fa0aa5b19079da872ea280961c9c96552f8be5539e1a0c050278187c3623"
  },
  {
    "time": "14:15",
    "quoteFirst": "\"Do you know it’s a ",
    "quoteTime": "quarter past two",
    "quoteLast": " and I’m due to play for the town on their ground at three.\"",
    "title": "Master and Maid",
    "author": "Harker, L. Allen (Lizzie Allen), 1863-1933",
    "gutenbergReference": "54504",
    "matchType": 1,
    "hash": "d4131b157a0e037e8e80cc85dc1dbee6393ec170906fb0dbbc929db992050fc8"
  },
  {
    "time": "14:15",
    "quoteFirst": "“That’s right, cousin,” answered Pieter, a pleasant-faced and alert young man, “look at _him_, scold _him_, for he is to blame. Ever since a ",
    "quoteTime": "quarter past two",
    "quoteLast": " have I—I who must drive a sledge in the great race and am backed to win—been waiting outside that factory in the snow, but, upon my honour, he did not appear until seven minutes since. Yes, we have done the whole distance in seven minutes, and I call that very good skating.",
    "title": "Lysbeth, a Tale of the Dutch",
    "author": "Haggard, H. Rider (Henry Rider), 1856-1925",
    "gutenbergReference": "5754",
    "matchType": 1,
    "hash": "cada3e2aefb21b029dfde0fa2f28d42430353ef2168de516898e289d0d78b303"
  },
  {
    "time": "14:15",
    "quoteFirst": "Nancy was temporarily working as a central in the Chesapeake and Potomac Telephone Company until she had taken her Civil Service examination for a Government position. “Well, about ",
    "quoteTime": "fifteen minutes after two",
    "quoteLast": " that morning a call came for the Trevors’ house.”",
    "title": "The Trevor case",
    "author": "Lincoln, Natalie Sumner, 1881-1935; Frederick, Edmund, 1870-1949 [Illustrator]",
    "gutenbergReference": "69004",
    "matchType": 1,
    "hash": "0ffb042caa03c3ecbfbc90c66aa74e0063eb6ff1d18e189bccae21cee2aa22c5"
  },
  {
    "time": "14:15",
    "quoteFirst": "Never had the preparation of a dinner seemed so slow to him, and a dozen times he found himself inwardly swearing at Tom, the Chinese cook. It was one o'clock before they sat down at the table and it was two o'clock when they arose. It was a ",
    "quoteTime": "quarter after two",
    "quoteLast": " when Joanne and he left the bungalow.",
    "title": "The Hunted Woman",
    "author": "Curwood, James Oliver, 1878-1927",
    "gutenbergReference": "11328",
    "matchType": 1,
    "hash": "0beb2a35fec66008c75b3721e6b461b911d55b133683c6dfe3ccbc52cb71b02e"
  },
  {
    "time": "14:15",
    "quoteFirst": "The next afternoon at a ",
    "quoteTime": "quarter past two",
    "quoteLast": " the committee was again in Baxter's office. Foley had been asked to come at half-past. The fifteen minutes before his expected arrival they spent in rehearsing the plan, so soon to be put to its severest test.",
    "title": "The Walking Delegate",
    "author": "Scott, Leroy, 1875-1929; Kinney, Margaret West, 1872-1952 [Illustrator]; Kinney, Troy, 1871-1938 [Illustrator]",
    "gutenbergReference": "41154",
    "matchType": 1,
    "hash": "0b057276a90a8da5b4db6dc8e60477a9cc674c2d0c2b8da83074cb65e293c8a3"
  },
  {
    "time": "14:15",
    "quoteFirst": "At a ",
    "quoteTime": "quarter after two",
    "quoteLast": " we left Newport's for home. We took in a little gasoline at Riverside. This was the only stop made on the home run, which was accomplished in three hours and a quarter (seventy-six miles) with a perfect score so far as the machine was concerned.",
    "title": "Out of Doors—California and Oregon",
    "author": "Graves, J. A. (Jackson Alpheus), 1852-1933",
    "gutenbergReference": "11517",
    "matchType": 1,
    "hash": "fae687fff949d94dcd99c4a4de99ae36444f509a3511bd097a47117f413f300e"
  },
  {
    "time": "14:15",
    "quoteFirst": "Taking three places, Margate, Gravesend, and London Bridge, we find that if the time of high tide at Margate is at noon on any day, then it is high tide at Gravesend at ",
    "quoteTime": "2.15 p.m.",
    "quoteLast": ", and at London Bridge a little before three o’clock. This difference is due to the time required for the tidal wave to travel up the estuary of the Thames.",
    "title": "Waves and ripples in water, air, and æther",
    "author": "Fleming, J. A. (John Ambrose), Sir, 1849-1945",
    "gutenbergReference": "71757",
    "matchType": 2,
    "hash": "d591a8c11de78b6fb8b2204eb43fbf7f26294848491d1db02b7059052d5d0fd9"
  },
  {
    "time": "14:15",
    "quoteFirst": "It was at exactly a ",
    "quoteTime": "quarter past two",
    "quoteLast": " that the work was finished.",
    "title": "The Pothunters",
    "author": "Wodehouse, P. G. (Pelham Grenville), 1881-1975",
    "gutenbergReference": "6984",
    "matchType": 1,
    "hash": "254f07cc1fe63bfcb73e958e816e5eab9504e667cfe70cddc4faf369b6fde8f9"
  },
  {
    "time": "14:15",
    "quoteFirst": "There were other odds and ends to be set in order, but he determined to let them wait until he had eaten. A scant half-hour in the club grill-room was all he allowed himself, and at a ",
    "quoteTime": "quarter past two",
    "quoteLast": " he was back at his desk, preparing to make the cleaning-up task complete. Between four and five, Judge Hemingway had said; and Blount began on one of the odds and ends, which was the writing of his letter of resignation from the railroad service.",
    "title": "The Honorable Senator Sage-Brush",
    "author": "Lynde, Francis, 1856-1930",
    "gutenbergReference": "16573",
    "matchType": 1,
    "hash": "f8c0385cd9dcab93af845e7d2cac20caa2f7fe426c0bd7a19ce6cfd84087547e"
  },
  {
    "time": "14:15",
    "quoteFirst": "and on to N.E. Two. From N.E. to the left round to N.N.W., then to the right a few paces to N. A ",
    "quoteTime": "quarter after two",
    "quoteLast": ". From N. and N. by E.: on the right some negroes, who remain in a very quiet posture; to the left W.N.W. Half-past two. W. by S., where we have a tolerably long road before us, then W.S.W.; on the right a small summer village.",
    "title": "Expedition to discover the sources of the White Nile, in the years 1840, 1841, Vol. 2 (of 2)",
    "author": "Werne, Ferdinand, 1800-1874; O'Reilly, Charles William [Translator]",
    "gutenbergReference": "73466",
    "matchType": 1,
    "hash": "8859d076002bac5aca22866d77784e9928deb634a361fca21b65c3764a984904"
  },
  {
    "time": "14:15",
    "quoteFirst": "I wonder wot ole 'Earty 'ud think. Well, I'm blowed! 'Ere, come along, sir!\" he cried to Mr. Dixon. \"It's a ",
    "quoteTime": "quarter past two",
    "quoteLast": ", we jest got a quarter of an hour;\" and the two men passed down the High Street in the direction of Putney Bridge.",
    "title": "Adventures of Bindle",
    "author": "Jenkins, Herbert George, 1876-1923",
    "gutenbergReference": "32285",
    "matchType": 1,
    "hash": "afc3a39f4b52e59f37f8bc8dd6f4a1a071bf2d0aa622e749783b951fe7d4a309"
  }
]