[
  {
    "time": "14:20",
    "quoteFirst": "“At ",
    "quoteTime": "2.20 P.M.",
    "quoteLast": " reports were received from _Galatea_ indicating the presence of enemy vessels. The direction of advance was immediately altered to S.S.E., the course for Horn Reef, so as to place my force between the enemy and his base.",
    "title": "The Grand Fleet, 1914-1916",
    "author": "Jellicoe, John Rushworth, 1859-1935",
    "gutenbergReference": "75323",
    "matchType": 2,
    "hash": "c554dd07baaebfebbe627d90db5b197ff7eac1d09ba02cd79226b663e3fd2887"
  },
  {
    "time": "14:20",
    "quoteFirst": "|       |        |    |    |     |           | These are called Estero, |       |        |    |    |     |           | Canoayacu, Matijuelo, and |       |        |    |    |     |           | Chumia, and are the most |       |        |    |    |     |           | difficult of the river. At |       |        |    |    |     |           | ",
    "quoteTime": "2.20 p.m.",
    "quoteLast": " arrived at Chasuta.",
    "title": "Exploration of the Valley of the Amazon, Part 1 (of 2)",
    "author": "Herndon, William Lewis, 1813-1857; Gibbon, Lardner, 1819-1910",
    "gutenbergReference": "57756",
    "matchType": 2,
    "hash": "f56dcec0e4138647f6f2e9c9b6925077184e71f7157b879802a7b436eef53b35"
  },
  {
    "time": "14:20",
    "quoteFirst": "January 20: ",
    "quoteTime": "2.20 p. m.",
    "quoteLast": ", 25 cc aqueous solution 2 per cent caffein (300 mg per kilo) were injected into the peritoneal cavity; 3.45 p. m., when doors of cage were opened rabbit had spasm of short duration.",
    "title": "The Toxicity of Caffein: An experimental study on different species of animals",
    "author": "Salant, William; Rieger, J. B. (John Benjamin), 1886-",
    "gutenbergReference": "46356",
    "matchType": 2,
    "hash": "45c7c3b05edf4c576aaf093b9f9a27d3ba71409e23d126b8c6c24af0c525783a"
  },
  {
    "time": "14:20",
    "quoteFirst": "Yardley had made first down; Dan saw the linesmen trot along with the poles and chain. He looked at his watch. The time was ",
    "quoteTime": "twenty minutes after two",
    "quoteLast": "; only fifteen minutes remained of the first half. If only he knew whether any scoring had been done! He believed that if he could get to the top of the window he could look over the corner of the nearest stand and see the score-board. But there was nothing to hold on by.",
    "title": "Forward Pass: A Story of the \"New Football\"",
    "author": "Barbour, Ralph Henry, 1870-1944",
    "gutenbergReference": "55982",
    "matchType": 1,
    "hash": "65524cb8f9b9986a2396cb4378e77b4c3423777cc5ee5b7a85b6252cf6f3e932"
  },
  {
    "time": "14:20",
    "quoteFirst": "Yardley had made first down; Dan saw the linesmen trot along with the poles and chain. He looked at his watch. The time was ",
    "quoteTime": "twenty minutes after two",
    "quoteLast": "; only fifteen minutes remained of the first half. If only he knew whether any scoring had been done! He believed that if he could get to the top of the window he could look over the corner of the nearest stand and see the score-board. But there was nothing to hold on by.",
    "title": "Forward Pass: A Story of the \"New Football\"",
    "author": "Barbour, Ralph Henry, 1870-1944",
    "gutenbergReference": "55982",
    "matchType": 1,
    "hash": "65524cb8f9b9986a2396cb4378e77b4c3423777cc5ee5b7a85b6252cf6f3e932"
  },
  {
    "time": "14:20",
    "quoteFirst": "On the Sunday before he went from his home in a gasoline boat in company with Clifton Gross, his son-in-law, to Athol, a railroad station on the Middle Fork of the Kentucky River, and thence on the following Monday he went to Jackson, which was the home of Fletch Deaton and of his codefendants, Red Tom Davidson and Govan Smith. Callahan was seen on the streets of Jackson on that day by several people. He left Jackson on the train at ",
    "quoteTime": "2.20 P. M.",
    "quoteLast": " for Louisville to buy a spring stock of goods for his store. His presence in Jackson, as well as his departure for Louisville and the purposes of his visit, were well known in Jackson.",
    "title": "Kentucky's Famous Feuds and Tragedies\r\nAuthentic History of the World Renowned Vendettas of the Dark and Bloody Ground",
    "author": "Mutzenberg, Charles Gustavus, 1863-",
    "gutenbergReference": "47201",
    "matchType": 2,
    "hash": "d57151b904a48642e71c8474b6b5680d75a587cbab94d7f9be1eecaa940e6db3"
  },
  {
    "time": "14:20",
    "quoteFirst": "_It was now ",
    "quoteTime": "2.20 p.m.",
    "quoteLast": "_",
    "title": "The Battle of Tsu-shima\nbetween the Japanese and Russian fleets, fought on 27th May 1905",
    "author": "Semenov, V. I. (Vladimir Ivanovich), 1867-1910; Lindsay, A. B. (Alexander Bertram), 1872-1914 [Translator]",
    "gutenbergReference": "57324",
    "matchType": 2,
    "hash": "5c63f952f15ae47c141183cf1146e592c76e20881a5a0e39b65569c0b80c246d"
  },
  {
    "time": "14:20",
    "quoteFirst": "The light cruiser _Galatea_ first sighted enemy ships at ",
    "quoteTime": "2.20 p.m.",
    "quoteLast": "  Soon she reported the smoke of a fleet, and at 3.31 Beatty sighted Hipper and formed his line of battle. At 3.",
    "title": "Days to Remember: The British Empire in the Great War",
    "author": "Buchan, John, 1875-1940; Newbolt, Henry John, Sir, 1862-1938",
    "gutenbergReference": "49540",
    "matchType": 2,
    "hash": "8d9ec23b5297aed8f5333b7e448227fbaddd11db0edf7b010a2e6136c364b3b2"
  },
  {
    "time": "14:20",
    "quoteFirst": "At ",
    "quoteTime": "2.20 p.m.",
    "quoteLast": " on February 24th, strong enemy forces debouched between =Louvemont= and =Hill 347=. During the night the first French reinforcements, belonging to the 20th C.A., repulsed them.",
    "title": "The Battle of Verdun (1914-1918)",
    "author": "Pneu Michelin (Firm) [Publisher]",
    "gutenbergReference": "53408",
    "matchType": 2,
    "hash": "9897d5247874afde6dd0ed689081c7eeb2b997957a421b3e80ac74758904a299"
  },
  {
    "time": "14:20",
    "quoteFirst": "the King from hustling down, as he always did, into the corner of his chair, where, with neck and chest bent forward, breathing was impossible,--at last took the King on his knee; kneeling on the ground with his other knee for the purpose,--King's right arm round Strutzki's neck, Strutzki's left arm round the King's back, and supporting his other shoulder; in which posture the faithful creature, for above two hours, sat motionless, till the end came. Within doors, all is silence, except this breathing; around it the dark earth silent, above it the silent stars. At ",
    "quoteTime": "20 minutes past 2",
    "quoteLast": ", the breathing paused,--wavered; ceased. Friedrich's Life-battle is fought out; instead of suffering and sore labor, here is now rest.",
    "title": "History of Friedrich II of Prussia — Volume 21",
    "author": "Carlyle, Thomas, 1795-1881",
    "gutenbergReference": "2121",
    "matchType": 1,
    "hash": "7fbaed41535ef24a323251630a8565c9864aa0c87a2856245eb4f893eb87854f"
  },
  {
    "time": "14:20",
    "quoteFirst": "Ellet, of the army, commanding, pushed up close to the fort. Each of the gunboats silenced the gun it was instructed to fire at about the same time. At ",
    "quoteTime": "twenty minutes past two",
    "quoteLast": " all the heavy smooth bore and rifled guns in the fort were most effectually silenced. The Black Hawk, Lieutenant-Commander K. R.",
    "title": "Pictorial history of the war for the Union, volume 2 (of 2)",
    "author": "Stephens, Ann S. (Ann Sophia), 1810-1886",
    "gutenbergReference": "74187",
    "matchType": 1,
    "hash": "a6dbad264a851e1b1bad7999e1ab566f634aabd0bf7c97f62589bcbf15eb1fb3"
  },
  {
    "time": "14:20",
    "quoteFirst": "Furthermore, it is ",
    "quoteTime": "twenty minutes past two",
    "quoteLast": ", and time to go to bed.",
    "title": "Life and Letters of Thomas Henry Huxley — Volume 1",
    "author": "Huxley, Thomas Henry, 1825-1895; Huxley, Leonard, 1860-1933 [Editor]",
    "gutenbergReference": "5084",
    "matchType": 1,
    "hash": "1cae44713887e19675eee32afcbc2b02b59e0121fa1331caaeafb7068dc989ac"
  },
  {
    "time": "14:20",
    "quoteFirst": "Yardley had made first down; Dan saw the linesmen trot along with the poles and chain. He looked at his watch. The time was ",
    "quoteTime": "twenty minutes after two",
    "quoteLast": "; only fifteen minutes remained of the first half. If only he knew whether any scoring had been done! He believed that if he could get to the top of the window he could look over the corner of the nearest stand and see the score-board. But there was nothing to hold on by.",
    "title": "Forward Pass: A Story of the \"New Football\"",
    "author": "Barbour, Ralph Henry, 1870-1944",
    "gutenbergReference": "55982",
    "matchType": 1,
    "hash": "65524cb8f9b9986a2396cb4378e77b4c3423777cc5ee5b7a85b6252cf6f3e932"
  },
  {
    "time": "14:20",
    "quoteFirst": "I reeled and nearly fell, so intoxicating was the effect of the gushing draught of sweet, fresh night-wind after the stagnant, cheesy atmosphere of the lazarette.  A bull's-eye shone on the face of a clock under the break of the poop; the hour was ",
    "quoteTime": "twenty minutes after two",
    "quoteLast": ".",
    "title": "International Short Stories: English",
    "author": "Patten, William, 1868-1936 [Editor]",
    "gutenbergReference": "32846",
    "matchType": 1,
    "hash": "105e3e0e00221fc09e04d97671bc4d944c454fc6e44aff45c6995f149fae7053"
  },
  {
    "time": "14:20",
    "quoteFirst": "About ",
    "quoteTime": "twenty minutes after two",
    "quoteLast": ", on this eventful day, the vast and gloomy shed of Waterloo lay, like the temple of a dead religion, silent and deserted. Here and there at one of the platforms, a train lay becalmed; here and there a wandering footfall echoed; the cab-horses outside stamped with startling reverberations on the stones; or from the neighbouring wilderness of railway an engine snorted forth a whistle.",
    "title": "The Works of Robert Louis Stevenson - Swanston Edition, Vol. 07",
    "author": "Stevenson, Robert Louis, 1850-1894",
    "gutenbergReference": "30807",
    "matchType": 1,
    "hash": "2438698027dd2c5eca5e21a25930b24b0508693698adf406033b28763451c7da"
  },
  {
    "time": "14:20",
    "quoteFirst": "February 27: 11.30 a. m., 15 cc 2 per cent caffein (210 mg per kilo) injected subcutaneously; ",
    "quoteTime": "2.20 p. m.",
    "quoteLast": ", no symptoms, tremors observed when handled, but not marked, reflexes slightly increased, no muscular rigidity nor any other symptoms; 2.45 p. m., rabbit suddenly became very restless, jumped off the table, and had convulsions; 3.45 p. m.",
    "title": "The Toxicity of Caffein: An experimental study on different species of animals",
    "author": "Salant, William; Rieger, J. B. (John Benjamin), 1886-",
    "gutenbergReference": "46356",
    "matchType": 2,
    "hash": "536f1de007af80aaf19e3568b8e24fde278325f5d42884bef275b0d38a1203ab"
  },
  {
    "time": "14:20",
    "quoteFirst": "June 6: ",
    "quoteTime": "2.20 p. m.",
    "quoteLast": ", 12 cc of 2 per cent caffein (0.28 gram per kilo) by mouth; 3 p. m., reflexes increased; 5 p. m., reflexes still more increased; no other symptoms.",
    "title": "The Toxicity of Caffein: An experimental study on different species of animals",
    "author": "Salant, William; Rieger, J. B. (John Benjamin), 1886-",
    "gutenbergReference": "46356",
    "matchType": 2,
    "hash": "7df2c09a707e98d31a5cc65041db846e7d46f469a4f953c78e912c72cc8d89d9"
  },
  {
    "time": "14:20",
    "quoteFirst": "The main Battle Cruiser Fleet and the Fifth Battle Squadron were considerably farther to the southward, and at ",
    "quoteTime": "2.20 p.m.",
    "quoteLast": " the light cruisers attached to this force signalled by wireless the first intimation that the enemy’s fleet was at sea. Subsequent reports confirmed this, and acting on the information contained in these intercepted messages, Rear-Admiral Hood ordered the ship’s companies to “Action Stations,” and shaped course to intercept the advancing enemy.",
    "title": "The Navy eternal",
    "author": "Bartimeus, 1886-1967; Swale, Douglas [Illustrator]",
    "gutenbergReference": "71548",
    "matchType": 2,
    "hash": "2e6fb0f67400506ae0037069f19a686c0e6b3f7e8d1e87845a00beddad850965"
  },
  {
    "time": "14:20",
    "quoteFirst": "It is clear that Dickens has intended to convey the impression that Edwin Drood is murdered, his body and clothes consumed, Jasper having first taken his watch and chain and shirt-pin, which cannot have been thrown into the river till the night of Christmas Day, since the watch, wound up at ",
    "quoteTime": "twenty minutes past two",
    "quoteLast": " on Christmas Eve, had run down when found in the river.",
    "title": "The Problem of 'Edwin Drood': A Study in the Methods of Dickens",
    "author": "Nicoll, W. Robertson (William Robertson), Sir, 1851-1923",
    "gutenbergReference": "36311",
    "matchType": 1,
    "hash": "a277b820b97b49a2af9a7a53072b61ab05477a341d486ebe001209e3be6f2c4e"
  },
  {
    "time": "14:20",
    "quoteFirst": "June 5: ",
    "quoteTime": "2.20 p. m.",
    "quoteLast": ", 25 cc of 2 per cent caffein (0.15 gram per kilo) given by mouth; 2.45 p. m., cat irritable, no other symptoms (cat did not vomit after the administration of caffein); 4 p. m.",
    "title": "The Toxicity of Caffein: An experimental study on different species of animals",
    "author": "Salant, William; Rieger, J. B. (John Benjamin), 1886-",
    "gutenbergReference": "46356",
    "matchType": 2,
    "hash": "3c29ad3247b014686ed44622dd3ae1b27dce73c409fb080e08af1108587ce1c0"
  }
]