[
  {
    "time": "16:20",
    "quoteFirst": "At ",
    "quoteTime": "4:20 p.m.",
    "quoteLast": " on Wednesday, we didn't need at all. (In The New Yorker, June 25, 1938) © 23Jun38; B381698.",
    "title": "U.S. Copyright Renewals 1950 - 1977",
    "author": "Library of Congress. Copyright Office",
    "gutenbergReference": "11800",
    "matchType": 2,
    "hash": "695c91fb78c4831ea0bbcc8ee076176443d016810aec0be3f57e2d5efb603d31"
  },
  {
    "time": "16:20",
    "quoteFirst": "P.M., when another shift favored the _President_, so that at ",
    "quoteTime": "4.20 P.M.",
    "quoteLast": "",
    "title": "The history of our Navy from its origin to the present day, 1775-1897, vol. 2 (of 4)",
    "author": "Spears, John Randolph, 1850-1936",
    "gutenbergReference": "71795",
    "matchType": 2,
    "hash": "e0a6bfa0ca3658c8a2d19ea097b4bc3d3b76bba079a4ae777959aaea97dd0174"
  },
  {
    "time": "16:20",
    "quoteFirst": "Black Watch, however, advanced at ",
    "quoteTime": "4.20 P.M.",
    "quoteLast": ", and attacked across the valley towards Chambrecy and east of the village. Violent machine and shell fire was opened on the battalions soon after they left the trenches in the Bois d'Éclisse; but in spite of their losses elements of the 7th Gordon Highlanders carried on, crossed the Bligny-Michel Renaut Farm road, and tried to make their way into the farm.",
    "title": "The History of the 51st (Highland) Division 1914-1918",
    "author": "Bewsher, F. W. (Frederick William), 1886-1950",
    "gutenbergReference": "45934",
    "matchType": 2,
    "hash": "a14f93511ef8290e52ba4f1a6be14a0603b0f6d8e91b0a8e3cecc8d641b20f8f"
  },
  {
    "time": "16:20",
    "quoteFirst": "Rather depends, you know, on what quarter the moon is in, and whether Mars and Venus are in conjunction, and Jupiter is in the First House, and the Sun is in Aries, and so on. But given that all these signs and portents are favorable, there is really no reason why muffins and salt and Chayney tea should not be perfectly delectable in Granny’s withdrawing-room at ",
    "quoteTime": "twenty minutes past four",
    "quoteLast": ", even after a champagne luncheon at Pagani’s at a quarter to two.",
    "title": "The principal girl",
    "author": "Snaith, J. C. (John Collis), 1876-1936",
    "gutenbergReference": "68069",
    "matchType": 1,
    "hash": "daf680cbef5b75d47993a9b1f64de07c1a4bfbb3f5f11b8c907541a51c906792"
  },
  {
    "time": "16:20",
    "quoteFirst": "\"Walk!\" repeated Sir Thomas, in a tone of most unanswerable dignity, and coming farther into the room. \"My niece walk to a dinner engagement at this time of the year! Will ",
    "quoteTime": "twenty minutes after four",
    "quoteLast": " suit you?\"",
    "title": "The Complete Project Gutenberg Works of Jane Austen\nA Linked Index of all PG Editions of Jane Austen",
    "author": "Austen, Jane, 1775-1817; Widger, David, 1932-2021? [Editor]",
    "gutenbergReference": "31100",
    "matchType": 1,
    "hash": "58199bab79acbb3dd9d064794f9e00c7d1a3a9c9b17c250d33343b985de6ef6b"
  },
  {
    "time": "16:20",
    "quoteFirst": "25       6th Dec.   4.10 P.M.   Found awake, washing her hands                            ? 26       7th Dec.   2.30 P.M.   Found asleep at 3.5                ? 27      10th Dec.   ",
    "quoteTime": "4.20 P.M.",
    "quoteLast": "   She was out walking                F.",
    "title": "Apparitions and thought-transference: an examination of the evidence for telepathy",
    "author": "Podmore, Frank, 1856-1910",
    "gutenbergReference": "56489",
    "matchType": 2,
    "hash": "fd3b3bd76ec58f1c06ed1bb0a2fd1bd99bbb1e977879609ce7061372a95b1cc3"
  },
  {
    "time": "16:20",
    "quoteFirst": "Mr. Molloy and his bride at about ",
    "quoteTime": "twenty minutes past four",
    "quoteLast": ". At 4:30 a natty two-seater car drew up at the gate of San Rafael and Willoughby Braddock alighted. Driving aimlessly about the streets of London some forty minutes earlier, and feeling rather at a loose end, it had occurred to him that a pleasant way of passing the evening would be to go down to Valley Fields and get Kay to give him a cup of tea.",
    "title": "Sam in the Suburbs",
    "author": "Wodehouse, P. G. (Pelham Grenville), 1881-1975",
    "gutenbergReference": "67368",
    "matchType": 1,
    "hash": "8c4322267f360a85a3a5dfb9f311c05177b9dffb2d9f67ba989eb8b19fcdeaa3"
  },
  {
    "time": "16:20",
    "quoteFirst": "At about ",
    "quoteTime": "twenty minutes past four",
    "quoteLast": " the leading files of the Zulus hove in sight, and the garrison of Rorke’s Drift flew to their several stations. Some went to the rampart of mealie-bags, others to the windows of the store-building, and others to the hospital where there had been forty-five men when the alarm first came, but where only twenty-three now remained.",
    "title": "The Book of the V.C.\r\nA record of the deeds of heroism for which the Victoria Cross has been bestowed, from its institution in 1857 to the present time",
    "author": "Haydon, A. L. (Arthur Lincoln), 1872-1964",
    "gutenbergReference": "55461",
    "matchType": 1,
    "hash": "dea7c82ef1210645eb4f497ea7c24f1a34a2826b810103f82f4024392a5b8aa0"
  },
  {
    "time": "16:20",
    "quoteFirst": "P.M., when another shift favored the _President_, so that at ",
    "quoteTime": "4.20 P.M.",
    "quoteLast": "",
    "title": "The history of our Navy from its origin to the present day, 1775-1897, vol. 2 (of 4)",
    "author": "Spears, John Randolph, 1850-1936",
    "gutenbergReference": "71795",
    "matchType": 2,
    "hash": "e0a6bfa0ca3658c8a2d19ea097b4bc3d3b76bba079a4ae777959aaea97dd0174"
  },
  {
    "time": "16:20",
    "quoteFirst": "It was a delicate tool to use in hardwood, but after lunch we managed to get the reach ready for use and were loaded up and off again at 3 P. M. We soon found we had our front stanchions on wrong and had to raise up the wagon and turn them, so that by the time we had this done, and had stopped at the section house for water, it was ",
    "quoteTime": "4:20 P. M.",
    "quoteLast": ", and we were only ten miles from our morning camp.",
    "title": "The Cruise of a Schooner",
    "author": "Harris, Albert W. (Albert Wadsworth), 1867-1958",
    "gutenbergReference": "42351",
    "matchType": 2,
    "hash": "a757b9f2d23645402e28d2036ca86f74962bc8fb39007884a277abf80b713e4c"
  },
  {
    "time": "16:20",
    "quoteFirst": "February 25, 4.15 p. m., 14 cc 2 per cent caffein (0.2 gram per kilo) injected into peritoneal cavity; ",
    "quoteTime": "4.20 p. m.",
    "quoteLast": ", restlessness and increased reflexes, rabbit found stretched out in cage, but raised himself on his legs again; 4.45, general tremor when touched.",
    "title": "The Toxicity of Caffein: An experimental study on different species of animals",
    "author": "Salant, William; Rieger, J. B. (John Benjamin), 1886-",
    "gutenbergReference": "46356",
    "matchType": 2,
    "hash": "95bb50c4e24861fac4992b126af7d79bcd3b9c49b544eb37b2ffd70e46fa3d79"
  },
  {
    "time": "16:20",
    "quoteFirst": "Passed to the south of the Fitzroy Range; the valley between it and Stokes' Range similar to Beagle Valley, and about four miles wide. Keeping close to Stokes' Range, passed behind some of the detached hills at ",
    "quoteTime": "4.20 p.m.",
    "quoteLast": " Reached our old camp of the 5th May, and found the stores we had left secreted in the rocks undisturbed.",
    "title": "Journals of Australian Explorations",
    "author": "Gregory, Augustus Charles, 1819-1905; Gregory, Francis Thomas, 1821-1888",
    "gutenbergReference": "10461",
    "matchType": 2,
    "hash": "f94653abe1ffac722293bbd448fc30c178a9e27b6d0f03ad894cb4c7c91863a5"
  },
  {
    "time": "16:20",
    "quoteFirst": "“At ",
    "quoteTime": "4.20 P.M.",
    "quoteLast": ", Sunday, we rolled out of the station at Omaha, and started westward on our long jaunt. A couple of hours out, dinner was announced—an “event” to those of us who had yet to experience what it is to eat in one of Pullman’s hotels on wheels; so, stepping into the car next forward of our sleeping palace, we found ourselves in the dining- car. It was a revelation to us, that first dinner on Sunday.",
    "title": "Roughing It",
    "author": "Twain, Mark, 1835-1910",
    "gutenbergReference": "3177",
    "matchType": 2,
    "hash": "8dec1b7df7e1d78a169198a941955ca6d08477014822e73fdbf9e72b55f02654"
  },
  {
    "time": "16:20",
    "quoteFirst": "\"At ",
    "quoteTime": "twenty minutes past four",
    "quoteLast": " Lord Melbourne returned. 'Well, Ma'am,' he said, 'we've considered this question, and both the sides of it well, and at last we voted upon it; and there were--the Lord Chancellor for dissolution, Lord Minto[38] for it, Lord Normanby against it, but greatly modified; Lord John for, Lord Palmerston for, Lord Clarendon for, Lord Morpeth for, Lord Lansdowne for, Labouchere for, Hobhouse for, Duncannon[39] for, Baring for, Macaulay for; and under those circumstances of course I felt I could not but go with them.[40] Lord Melbourne was much affected in saying all this.",
    "title": "The letters of Queen Victoria, vol. 1, 1837-1843",
    "author": "Victoria, Queen of Great Britain, 1819-1901; Benson, Arthur Christopher, 1862-1925 [Editor]; Esher, Reginald Baliol Brett, Viscount, 1852-1930 [Editor]",
    "gutenbergReference": "20023",
    "matchType": 1,
    "hash": "b5c9add2c9cdecf71bdd1494e584565f114e87c67231824d87a68e27212f7416"
  },
  {
    "time": "16:20",
    "quoteFirst": "Captain Hoppner had scarcely been an hour on board the Fury, and was busily engaged in getting the anchors and cables on board, when we observed some large pieces of not very heavy ice closing in with the land near her; and at ",
    "quoteTime": "twenty minutes past four P.M.",
    "quoteLast": ", being an hour and five minutes after the Hecla had cast off, I was informed by signal that the Fury was on shore. As the navigating of the Hecla, with only ten men on board, required constant attention and care, I could not at this time, with propriety, leave the ship to go on board the Fury.",
    "title": "Three Voyages for the Discovery of a Northwest Passage from the Atlantic to the Pacific, and Narrative of an Attempt to Reach the North Pole, Volume 2",
    "author": "Parry, William Edward, Sir, 1790-1855",
    "gutenbergReference": "14350",
    "matchType": 0,
    "hash": "af5619501ae5560eec02622c048a15643d8aee5a985ee16a5221b02b5d62d8fa"
  },
  {
    "time": "16:20",
    "quoteFirst": "Course, always south with few turns. My sponging-bath makes a good pinnace for going ashore from the vessel. At ",
    "quoteTime": "4.20 P.M.",
    "quoteLast": " one of the noggurs carried away her yard--the same boat that met with the accident at our departure; hove to, and closed with the bank for repairs. Here is an affair of delay; worked with my own hands until 9 p.m.; spliced the yard, bound it with rhinoceros thongs, and secured the whole splice with raw bull's hide. Posted sentries--two on each boat, and two on shore.",
    "title": "The Albert N'Yanza, Great Basin of the Nile, And Explorations of the Nile Sources",
    "author": "Baker, Samuel White, Sir, 1821-1893",
    "gutenbergReference": "3668",
    "matchType": 2,
    "hash": "9f4c8f84eda6e8c1f87fe6f6f00e44328984670ca9011bdf1ef571e8ed04dfe7"
  },
  {
    "time": "16:20",
    "quoteFirst": "Cradock spread out his four ships, fifteen miles apart, and steamed to the north-west at ten knots. Smoke became visible to the _Glasgow_ at ",
    "quoteTime": "4.20 p.m.",
    "quoteLast": ", and as she increased speed to investigate, there appeared two four-funnelled armoured cruisers and one light cruiser with three funnels. Those four-funnelled ships were the _Scharnhorst_ and _Gneisenau_, and until they were seen at that moment by the _Glasgow_ they were not positively known to have been on the Chilean coast.",
    "title": "The Silent Watchers\nEngland's Navy during the Great War: What It Is, and What We Owe to It",
    "author": "Copplestone, Bennet, 1867-1932",
    "gutenbergReference": "48497",
    "matchType": 2,
    "hash": "9216d936f78b32f99f288bdba7739bfb87227819c215bacd7d0210480e9e2c86"
  },
  {
    "time": "16:20",
    "quoteFirst": "At ",
    "quoteTime": "4.20 p.m.",
    "quoteLast": " on October 22, Putney, Crowder, and Vauxhall bridges were destroyed by shell fire while a relief was in progress, and the enemy continued to shell the area to prevent repairs. Lieutenant J. F. H. Nicholson, Corporal Brightmore, and Sappers J. Bennett and J.",
    "title": "The 42nd (East Lancashire) Division 1914-1918",
    "author": "Gibbon, Frederick P.",
    "gutenbergReference": "73544",
    "matchType": 2,
    "hash": "efc1822e649db3d0f57b9acfeed9d336b4f8266fb0467abf605fcdddcc57abcf"
  },
  {
    "time": "16:20",
    "quoteFirst": "\"At ",
    "quoteTime": "4.20 P.M.",
    "quoteLast": ", Sunday, we rolled out of the station at Omaha, and started westward on our long jaunt.  A couple of hours out, dinner was announced--an \"event\" to those of us who had yet to experience what it is to eat in one of Pullman's hotels on wheels; so, stepping into the car next forward of our sleeping palace, we found ourselves in the dining-car.",
    "title": "Roughing It, Part 1.",
    "author": "Twain, Mark, 1835-1910",
    "gutenbergReference": "8582",
    "matchType": 2,
    "hash": "fe27eb9b63dba3b6b3130dd171d6eec3fad45d7309c17b7a8d47824e440ff6e8"
  },
  {
    "time": "16:20",
    "quoteFirst": "I pulled out my watch, which I had forgotten to wind; and found it run down. The hands stood at ",
    "quoteTime": "twenty minutes past four",
    "quoteLast": ". Daylight, then, could not be far off. Eighteen hours--say twenty: and Byfield had guessed our rate at one time to be thirty miles an hour.",
    "title": "The Works of Robert Louis Stevenson - Swanston Edition, Vol. 20",
    "author": "Stevenson, Robert Louis, 1850-1894; Quiller-Couch, Arthur, 1863-1944 [Contributor]",
    "gutenbergReference": "30849",
    "matchType": 1,
    "hash": "b6d6ac53a8bd3e18b0b479c601a2b6517b66fed15cd5a514b2d92f1593688f1b"
  }
]