[
  {
    "time": "22:36",
    "quoteFirst": "|               |   Calling him; no answer. |               | ",
    "quoteTime": "10.36 p. m.",
    "quoteLast": "| 12.25 a. m.   | M. G. Y. (Titanic) says CQD. Here corrected |               |   position 41.46 N., 50.14 W. |               |   Require immediate assistance.",
    "title": "Loss of the Steamship \"Titanic\"",
    "author": "Great Britain. Court to investigate loss of steamship \"Titanic\"",
    "gutenbergReference": "39415",
    "matchType": 2,
    "hash": "6ee2566f05f0e98bdcea1ac0dde4910730455b7c7252f96b081fd3a9c53aa1c4"
  }
]