[
  {
    "time": "06:44",
    "quoteFirst": "This was precisely at sunset, or ",
    "quoteTime": "forty-four minutes past six",
    "quoteLast": ".\"",
    "title": "Deeds that Won the Empire\nHistoric Battle Scenes",
    "author": "Fitchett, W. H. (William Henry), 1845-1928",
    "gutenbergReference": "19255",
    "hash": "8edd6d2d854252c2d7adfabbe2ed16f2c89fee90d26515cdbe762a0e4334388a"
  },
  {
    "time": "06:44",
    "quoteFirst": "Investigations proved that he had left the building at precisely ",
    "quoteTime": "sixteen minutes of seven",
    "quoteLast": ", the janitor declaring that he had looked at his watch the instant the old man appeared on the sidewalk where he was shovelling away the snow.",
    "title": "Mr. Bingle",
    "author": "McCutcheon, George Barr, 1866-1928",
    "gutenbergReference": "5963",
    "hash": "8a85a50231c9a556226d011a8d4e119e053b7b9be8fc6b5cda9610bff8d0f75d"
  }
]