[
  {
    "time": "10:05",
    "quoteFirst": "\"It'll be about ",
    "quoteTime": "five minutes past ten",
    "quoteLast": ", your honour, by my watch.\"",
    "title": "The Adventures of a Three-Guinea Watch",
    "author": "Reed, Talbot Baines, 1852-1893",
    "gutenbergReference": "21035",
    "hash": "9edfbc477b8659eb6f10bcb3be431a787b3ab67831ccf38616120245147423c6"
  },
  {
    "time": "10:05",
    "quoteFirst": "_Monday Morning._--A fine clear frosty morning with a sharp wind. I walked to Keswick. Set off at ",
    "quoteTime": "5 minutes past 10",
    "quoteLast": ", and arrived at 1/2 past 2. I found them all well.",
    "title": "Journals of Dorothy Wordsworth, Vol. 1 (of 2)",
    "author": "Wordsworth, Dorothy, 1771-1855; Knight, William Angus, 1836-1916 [Editor]",
    "gutenbergReference": "42856",
    "hash": "dc7617117867255c9e5325be72ff548175089881eb3ce3075ce5c5e73962df68"
  },
  {
    "time": "10:05",
    "quoteFirst": "\"At ",
    "quoteTime": "five minutes past ten",
    "quoteLast": " a man of mine, still a little out of breath from his haste, comes to us in the Grande Taverne and tells us that Jean Cladel has just reached home.  He reached home then at five minutes to ten.\"",
    "title": "The House of the Arrow",
    "author": "Mason, A. E. W. (Alfred Edward Woodley), 1865-1948",
    "gutenbergReference": "67514",
    "hash": "043a6736b7d827a7d38e165b8b0f4bb7579ee2d0a0a02eada8f8907ec85ce2aa"
  },
  {
    "time": "10:05",
    "quoteFirst": "“The Action began at ",
    "quoteTime": "five minutes past ten",
    "quoteLast": ". In about half an hour afterwards, the first half of our Fleet was engaged, and before half-past eleven, the Battle became general. The _Elephant’s_ station was in the centre, opposite to the Danish Commodore.... The judgment with which each Ship calculated her station in that intricate Channel, was admirable throughout.",
    "title": "The Boys' Nelson",
    "author": "Wheeler, Harold, 1877-",
    "gutenbergReference": "50731",
    "hash": "d3b7e78ed885cf8262bf1e23d1b49bb97418af1d5c466e3ca45a73daf11402c3"
  },
  {
    "time": "10:05",
    "quoteFirst": "He looked at his breakfast, pecked at a sole, and at nine-fifteen, feeling distinctly unwell, he took a taxi for the course. He had one great consolation upholding him. At ",
    "quoteTime": "five minutes past ten",
    "quoteLast": " it would all be over. He felt that he knew how glad a condemned criminal must be that at five minutes past eight on a certain morning--or a minute or two earlier with a little luck--a black flag would be hoisted on the prison pole.",
    "title": "The Happy Golfer\r\nBeing Some Experiences, Reflections, and a Few Deductions of a Wandering Golfer",
    "author": "Leach, Henry, 1874-",
    "gutenbergReference": "37136",
    "hash": "381e9897ad1a813a80755ad4198af5a2f7fc306de6fd3fe2376f30c6670d3d6f"
  },
  {
    "time": "10:05",
    "quoteFirst": "Unhappy father! he strives to remember, perhaps persuades himself that he does remember, that on the evening of the murder he was himself at home at ten o'clock. He thinks, or seems to think, that his son came in at about ",
    "quoteTime": "five minutes past ten",
    "quoteLast": ". He fancies that he remembers his conversation; he thinks he spoke of bolting the door; he thinks he asked the time of night; he seems to remember his then going to his bed. Alas! these are but the swimming fancies of an agitated and distressed mind.",
    "title": "The Great Speeches and Orations of Daniel Webster\r\nWith an Essay on Daniel Webster as a Master of English Style",
    "author": "Webster, Daniel, 1782-1852; Whipple, Edwin Percy, 1819-1886",
    "gutenbergReference": "12606",
    "hash": "8fa0ecd526f22b2532fbb43b462ad65bb03ba90b0ddfd649fc75267a6b486c01"
  },
  {
    "time": "10:05",
    "quoteFirst": "\"",
    "quoteTime": "Five minutes past ten",
    "quoteLast": ".\"",
    "title": "The Seventh Noon",
    "author": "Bartlett, Frederick Orin, 1876-1945; Frederick, Edmund, 1870-1949 [Illustrator]",
    "gutenbergReference": "20429",
    "hash": "49fd3de8ebe36e0be5d316988fca2ee93205b435d3dac5041340972f4ab4dfae"
  },
  {
    "time": "10:05",
    "quoteFirst": "“To show him this letter! Don’t be alarmed—the lady does not eye Llewellyn’s suit with any favor. She has threatened him doubtless that if he continued to pester her with his attentions, she would report the whole affair to Stewart. Somewhere about ",
    "quoteTime": "five minutes past ten",
    "quoteLast": " on the fatal night—she did so.”",
    "title": "The case of the Black Twenty-Two",
    "author": "Flynn, Brian, 1885-1958",
    "gutenbergReference": "75209",
    "hash": "222842b0a1322e83915f5af2d15589f94de6e9c4ce8753acb59268099775673c"
  },
  {
    "time": "10:05",
    "quoteFirst": "This was precisely what I expected. A vagabond like Mr. Jay knows the importance of giving himself a respectable look when he is going to run the risk of changing a stolen bank-note. At ",
    "quoteTime": "five minutes past ten",
    "quoteLast": " o'clock he had given the last brush to his shabby hat and the last scouring with bread-crumb to his dirty gloves. At ten minutes past ten he was in the street, on his way to the nearest cab-stand, and I and my subordinates were close on his heels.",
    "title": "Masterpieces of Mystery in Four Volumes: Detective Stories",
    "author": "French, Joseph Lewis, 1858-1936 [Editor]",
    "gutenbergReference": "27523",
    "hash": "e2a854f1a5367e51986800ca60bbce259b3c82dcc2ec3f925279189ec3eb02b6"
  },
  {
    "time": "10:05",
    "quoteFirst": "\"At ",
    "quoteTime": "five minutes past ten",
    "quoteLast": ", two sergents de ville, disguised as bourgeois, were brought in by the francs-tireurs and immediately shot.",
    "title": "Paris from the Earliest Period to the Present Day; Volume 1",
    "author": "Walton, William, 1843-1915",
    "gutenbergReference": "30651",
    "hash": "5fd6f16340b1b40c6281eb3a29354eb6a4359080adf877ad9278cca2a7b18a9c"
  },
  {
    "time": "10:05",
    "quoteFirst": "Before tackling this last obstacle, we paused for a rest and some hot coffee from the thermos which was included in our equipment. Then, at ",
    "quoteTime": "five minutes past ten",
    "quoteLast": ", we started the final ascent.",
    "title": "The Image and the Likeness",
    "author": "Campbell, John Scott",
    "gutenbergReference": "37145",
    "hash": "8a2ba13ecd0b6c6a7547883a902b6432df42beb7aaab781c12080abc4872118d"
  },
  {
    "time": "10:05",
    "quoteFirst": "The testimony of Edgar Leon Smith, Jr. was taken at ",
    "quoteTime": "10:05 a.m.",
    "quoteLast": ", on July 24, 1964, in the office of the U.S. attorney, 301 Post Office Building, Bryan and Ervay Streets, Dallas, Tex., by Mr. Wesley J.",
    "title": "Warren Commission (07 of 26): Hearings Vol. VII (of 15)",
    "author": "United States. Warren Commission",
    "gutenbergReference": "44007",
    "hash": "aecbecd94437bd6aa1df548edc409ae99fb6b089815536695618c9f41630c97c"
  },
  {
    "time": "10:05",
    "quoteFirst": "The clock at Nicholson’s Brewery showed ",
    "quoteTime": "five minutes past ten",
    "quoteLast": " as they crawled down into the town; opened out again for the Bridge; swished over it past Skindle’s Hotel.",
    "title": "Peter Jameson: A Modern Romance",
    "author": "Frankau, Gilbert, 1884-1952",
    "gutenbergReference": "59936",
    "hash": "1fdb7977fa5b772e199f389008bb06aeffd31b56623533b423217e1bc8545143"
  },
  {
    "time": "10:05",
    "quoteFirst": "“To show him this letter! Don’t be alarmed—the lady does not eye Llewellyn’s suit with any favor. She has threatened him doubtless that if he continued to pester her with his attentions, she would report the whole affair to Stewart. Somewhere about ",
    "quoteTime": "five minutes past ten",
    "quoteLast": " on the fatal night—she did so.”",
    "title": "The case of the Black Twenty-Two",
    "author": "Flynn, Brian, 1885-1958",
    "gutenbergReference": "75209",
    "hash": "222842b0a1322e83915f5af2d15589f94de6e9c4ce8753acb59268099775673c"
  },
  {
    "time": "10:05",
    "quoteFirst": "“The Action began at ",
    "quoteTime": "five minutes past ten",
    "quoteLast": ". In about half an hour afterwards, the first half of our Fleet was engaged, and before half-past eleven, the Battle became general. The _Elephant’s_ station was in the centre, opposite to the Danish Commodore.... The judgment with which each Ship calculated her station in that intricate Channel, was admirable throughout.",
    "title": "The Boys' Nelson",
    "author": "Wheeler, Harold, 1877-",
    "gutenbergReference": "50731",
    "hash": "d3b7e78ed885cf8262bf1e23d1b49bb97418af1d5c466e3ca45a73daf11402c3"
  },
  {
    "time": "10:05",
    "quoteFirst": "The clock at Nicholson’s Brewery showed ",
    "quoteTime": "five minutes past ten",
    "quoteLast": " as they crawled down into the town; opened out again for the Bridge; swished over it past Skindle’s Hotel.",
    "title": "Peter Jameson: A Modern Romance",
    "author": "Frankau, Gilbert, 1884-1952",
    "gutenbergReference": "59936",
    "hash": "1fdb7977fa5b772e199f389008bb06aeffd31b56623533b423217e1bc8545143"
  },
  {
    "time": "10:05",
    "quoteFirst": "At ",
    "quoteTime": "five minutes past ten",
    "quoteLast": " a youth entered with the \"Times\" under his arm. Richard waited for him to speak, but he merely stared and took off his overcoat.",
    "title": "A Man from the North",
    "author": "Bennett, Arnold, 1867-1931",
    "gutenbergReference": "52247",
    "hash": "a07aa7400aaf3a203d9a7842237db738dd4c0f48a25aed672dc39352c6a2b1c0"
  },
  {
    "time": "10:05",
    "quoteFirst": "\"",
    "quoteTime": "Five minutes past ten",
    "quoteLast": ".\"",
    "title": "Officer 666",
    "author": "Currie, Barton Wood, 1877-1962; McHugh, Augustin, 1877-1928",
    "gutenbergReference": "30228",
    "hash": "ddc3961d295fd42ca0f36bd91da9a782e99e45d153bf5cfbf77a25bc08a49d91"
  },
  {
    "time": "10:05",
    "quoteFirst": "There was less trouble in his classes nowadays, possibly because the whole school was so much interested in football, and it began to look as though the instructor’s troubles were over. But on the following Tuesday, Brandon Gary, realizing possibly, that he had neglected his duties as a cut-up, gave his attention again to Mr. Hanks. That was at ",
    "quoteTime": "five minutes past ten",
    "quoteLast": ".",
    "title": "Crofton Chums",
    "author": "Barbour, Ralph Henry, 1870-1944; Relyea, C. M. (Charles M.), 1863-1932 [Illustrator]",
    "gutenbergReference": "60894",
    "hash": "95def634687fc24b934dbca08a13968494a93cdbb2c1238f0f06f5d37e443589"
  },
  {
    "time": "10:05",
    "quoteFirst": "Stultz to India in the year 1821—he never once thinks of disobeying Mrs. Newcome’s order, but is actually at her door at ",
    "quoteTime": "five minutes past ten",
    "quoteLast": ", having arrayed himself to the wonderment of Clive, and left the boy to talk with his friend and fellow-passenger, Mr. Binnie, who has just arrived from Portsmouth, who has dined with him, and who, by previous arrangement, has taken up his quarters at the same hotel.",
    "title": "The Newcomes: Memoirs of a Most Respectable Family",
    "author": "Thackeray, William Makepeace, 1811-1863",
    "gutenbergReference": "7467",
    "hash": "4af326b70aa74fdba424d6f3faa7879e4f53ead87e35d3e196e5735bfacf6669"
  }
]