[
  {
    "time": "11:10",
    "quoteFirst": "In another two minutes Mr. Prokofieff will go mad. They should have started at eleven. It is now ",
    "quoteTime": "ten minutes after eleven",
    "quoteLast": ". And they have not yet started. Ah, Mr.",
    "title": "A Thousand and One Afternoons in Chicago",
    "author": "Hecht, Ben, 1894-1964",
    "gutenbergReference": "7988",
    "hash": "45762da7f0876a482cbe1de7f22def8a9b5825c0834f171fc071e4839f92cb93"
  },
  {
    "time": "11:10",
    "quoteFirst": "May 26: 10.05 a. m., 22 cc 2 per cent caffein (0.3 gram per kilo) injected subcutaneously; ",
    "quoteTime": "11.10 a. m.",
    "quoteLast": ", copious salivation, cat irritable, muscular stiffness present, but no tetanus; 11.45 a. m., cat restless, convulsions, attacks of short duration, no paralysis observed after the convulsions, pupils dilated; 4.45 p. m.",
    "title": "The Toxicity of Caffein: An experimental study on different species of animals",
    "author": "Salant, William; Rieger, J. B. (John Benjamin), 1886-",
    "gutenbergReference": "46356",
    "hash": "6dfc3cac385676624def6455d75db572917d2bb50a0a1e4d31fbf99e5b0dca7a"
  },
  {
    "time": "11:10",
    "quoteFirst": "Received at ",
    "quoteTime": "11.10 a.m.",
    "quoteLast": " from 30th American Division:",
    "title": "The Australian Victories in France in 1918",
    "author": "Monash, John, Sir, 1865-1931",
    "gutenbergReference": "51163",
    "hash": "cc02dc35e6ae6aff7159c921763a32bd4acf5dc2d47ca48c26f22355768c9d59"
  },
  {
    "time": "11:10",
    "quoteFirst": "“No, but this morning is exceptional. I really must ask you to go—” she glanced at the clock. It was nearly ",
    "quoteTime": "ten minutes past eleven",
    "quoteLast": ", and royalty was hideously prompt. “I dislike being rude, but I must ask you to go at once.",
    "title": "Julia France and Her Times: A Novel",
    "author": "Atherton, Gertrude Franklin Horn, 1857-1948",
    "gutenbergReference": "57922",
    "hash": "cf6a2d9f0fc277e08499ec10de277a59a7f838f12a249b9f08223de5df82d633"
  },
  {
    "time": "11:10",
    "quoteFirst": "She rightly conjectured that, after the affair of the store-cupboard in the garden-room, there could be nothing of lesser importance than \"the duel\" which could take that lady through those abhorred portals. Finally, at ",
    "quoteTime": "ten minutes past eleven",
    "quoteLast": ", Major Flint and Captain Puffin were seen by one or two fortunate people (the morning having cleared up) walking together to the tram, and, without exception, everybody knew that they were on their way to fight their duel in some remote hollow of the sand-dunes.",
    "title": "Miss Mapp",
    "author": "Benson, E. F. (Edward Frederic), 1867-1940",
    "gutenbergReference": "25919",
    "hash": "0e871d3d6597aec04b349ddcd63e301a49d7b0532a87b57b667d7e223f4bb0c7"
  },
  {
    "time": "11:10",
    "quoteFirst": "At eleven they met the Marquise de Beau Séjour leaving her Majesty’s apartments. The Chevalier spoke to her, the King did not. At ",
    "quoteTime": "ten minutes past eleven",
    "quoteLast": " His Majesty went to bed.”",
    "title": "\"No. 101\"",
    "author": "Carey, Wymond, 1869-1948; Paget, Walter, 1863-1935 [Illustrator]",
    "gutenbergReference": "69819",
    "hash": "3b75722010bbe198f436149b1f5d83feae2204e6c4ba1d5e62be41ae55ac1f94"
  },
  {
    "time": "11:10",
    "quoteFirst": "Received at ",
    "quoteTime": "11.10 a.m.",
    "quoteLast": " from 30th American Division:",
    "title": "The Australian Victories in France in 1918",
    "author": "Monash, John, Sir, 1865-1931",
    "gutenbergReference": "51163",
    "hash": "cc02dc35e6ae6aff7159c921763a32bd4acf5dc2d47ca48c26f22355768c9d59"
  },
  {
    "time": "11:10",
    "quoteFirst": "He reads the telegram three times before he fully grasps its signification; and it is quite two minutes before it occurs to him to look at its date. 'Sent out at ",
    "quoteTime": "11.10 A.M.",
    "quoteLast": " Received at 11.35.' It has been lying waiting for him for fourteen hours and more. He reads it a fourth time. 'Come at once, and without a moment's delay, on receipt of this.",
    "title": "Doctor Cupid: A Novel",
    "author": "Broughton, Rhoda, 1840-1920",
    "gutenbergReference": "35548",
    "hash": "a58a6fa059b51c41e8f411c1e5b39382c1e1dd350a249affe09374798dde3c68"
  },
  {
    "time": "11:10",
    "quoteFirst": "All these things, combined with the noises and interruptions of constant comings in and goings out, made Mr. Pickwick play rather badly; the cards were against him also; and when they left off at ",
    "quoteTime": "ten minutes past eleven",
    "quoteLast": ", Miss Bolo rose from the table considerably agitated, and went straight home, in a flood of tears, and a sedan chair.",
    "title": "The Posthumous Papers of the Pickwick Club, v. 2 (of 2)",
    "author": "Dickens, Charles, 1812-1870; Aldin, Cecil, 1870-1935 [Illustrator]",
    "gutenbergReference": "47535",
    "hash": "baa49c00c68617bd60717802d22cf5522a14a78e559969aa9e53ecff87395579"
  },
  {
    "time": "11:10",
    "quoteFirst": "",
    "quoteTime": "Ten minutes after eleven",
    "quoteLast": "—why that would be only ten minutes after six in New York! How plainly he could picture the familiar scenes of rushing, bustling life back there! Crowds were now pouring into the subways and surface cars or climbing to the level of the \"L's.\" This was the third—the latest homeward wave.",
    "title": "Time Telling through the Ages",
    "author": "Brearley, Harry Chase, 1870-1940",
    "gutenbergReference": "47928",
    "hash": "00bf3f7f5d5299971cb76c065b737453cef33cc0d8e164fff1295e4f8a56268b"
  },
  {
    "time": "11:10",
    "quoteFirst": "I went down the street to my car and started the engine and kept it going to be ready while I watched. ",
    "quoteTime": "Ten minutes past eleven",
    "quoteLast": ", I saw a light in Win Scofield’s garage; a black car came out and a girl got into it. I waited until it was in the street and then, stepping on my gas, I charged up the road and gave that black car all I had.",
    "title": "Keeban",
    "author": "Balmer, Edwin, 1883-1959",
    "gutenbergReference": "66114",
    "hash": "0bff1800c6528a502aa8b017bc9691b0255096389c72fd5918ced690ab380180"
  },
  {
    "time": "11:10",
    "quoteFirst": "28, 2 cc 2 per cent caffein injected, convulsions; 10.29, convulsions stopped; 10.32, convulsions; 11 a. m., rabbit lying on its side, anterior extremities paralyzed, posterior extremities contracted, no clonic convulsions, breathed deeper and more slowly than normal; ",
    "quoteTime": "11.10 a. m.",
    "quoteLast": ", rabbit died, had no convulsions immediately before death; amount of caffein injected, 11 cc 2 per cent solution, or 0.166 gram per kilo.",
    "title": "The Toxicity of Caffein: An experimental study on different species of animals",
    "author": "Salant, William; Rieger, J. B. (John Benjamin), 1886-",
    "gutenbergReference": "46356",
    "hash": "1fad7dce493baa689e19028233bcc456d4b79910aaa0a65142ddd29a887be957"
  },
  {
    "time": "11:10",
    "quoteFirst": "\"It's ",
    "quoteTime": "ten minutes past eleven",
    "quoteLast": "!\" somebody yelled.",
    "title": "We Were There at the Oklahoma Land Run",
    "author": "Kjelgaard, Jim, 1910-1959; Kenyon, Chris A. [Illustrator]; Lottinville, Savoie, 1906-1997 [Other]",
    "gutenbergReference": "34720",
    "hash": "d8125b0e72ae64b94aeeb611a1fce56b6fbe7806c06d2dea84049b6e2e5f8076"
  },
  {
    "time": "11:10",
    "quoteFirst": "She rightly conjectured that, after the affair of the store-cupboard in the garden-room, there could be nothing of lesser importance than \"the duel\" which could take that lady through those abhorred portals. Finally, at ",
    "quoteTime": "ten minutes past eleven",
    "quoteLast": ", Major Flint and Captain Puffin were seen by one or two fortunate people (the morning having cleared up) walking together to the tram, and, without exception, everybody knew that they were on their way to fight their duel in some remote hollow of the sand-dunes.",
    "title": "Miss Mapp",
    "author": "Benson, E. F. (Edward Frederic), 1867-1940",
    "gutenbergReference": "25919",
    "hash": "0e871d3d6597aec04b349ddcd63e301a49d7b0532a87b57b667d7e223f4bb0c7"
  },
  {
    "time": "11:10",
    "quoteFirst": "In a faltering voice he narrated the history of the evening: the merry dinner-party, the sound of the lively music upstairs (Minna’s mad tarantella), the angry words he had overheard on coming into his master’s study, the permission to go to bed, his last sight of the prisoner at ",
    "quoteTime": "ten minutes past eleven",
    "quoteLast": ", his after meeting with Mr. Hart in the bedroom at five minutes to twelve, when the latter had taken the ledger from his bedroom safe and gone downstairs again. Familiar as all these facts were to Irene, every fresh statement put them in a still more terrible light.",
    "title": "Idols",
    "author": "Locke, William John, 1863-1930",
    "gutenbergReference": "56015",
    "hash": "83902d66d2ea57c3f576fb333faee3b34a0fb7adb23115d57eb65a2ef9630f23"
  },
  {
    "time": "11:10",
    "quoteFirst": "Our servants were so numbed and stupefied by it that we could not get them to move till they had had some hours sunning. We got away at ",
    "quoteTime": "11.10 A.M.",
    "quoteLast": ", and proceeded northwards over an undulating plain bounded on the east and west by low hills. The width of the plain is about six miles, and its surface presents nothing but an unvaried scrub of wormwood growing on a soft, spongy, and gravelly soil.",
    "title": "From the Indus to the Tigris",
    "author": "Bellew, H. W. (Henry Walter), 1834-1892",
    "gutenbergReference": "74127",
    "hash": "c23f1316e5c30e3a6193b60fd6cee6fba3086ed272e94e8e8fdc9c4618b88165"
  },
  {
    "time": "11:10",
    "quoteFirst": "The details mentioned above will proceed via trenches, leaving same at junction of _Tipperary_ trench and _Rams Horn_ boyau in the following order: Co. D: Detail will clear junction _Rams Horn_ boyau and _Tipperary_ trench at 5.40 a.m., ",
    "quoteTime": "11.10 a.m.",
    "quoteLast": " and 4.40 p.m.",
    "title": "Military Instructors Manual",
    "author": "Cole, J. P. (James Perry), 1889-1977; Schoonmaker, Oliver, 1882-1968",
    "gutenbergReference": "14625",
    "hash": "724184534930b6bb6081cf5baecc3ec3bc16497aca8a822cb0b052b1a6411eb4"
  },
  {
    "time": "11:10",
    "quoteFirst": "At ",
    "quoteTime": "ten minutes past eleven",
    "quoteLast": " our light cavalry brigade advanced.",
    "title": "Ten Englishmen of the Nineteenth Century",
    "author": "Joy, James Richard, 1863-1957",
    "gutenbergReference": "5876",
    "hash": "f6be67e0c04b6dd050ad8e0f157ca9e7b85b7649f799980b01634f6bcb2364ba"
  },
  {
    "time": "11:10",
    "quoteFirst": "It ran from the \"White Horse\" Cellars every Tuesday, Thursday, and Saturday during the season, returning from the \"George,\" Portsmouth, on Mondays, Wednesdays, and Fridays. In the earlier years of its running, the \"Rocket\" made good time, taking eight and a half hours, up or down; but its quickest time was made on the down journey during the season of 1881, when it left Piccadilly at ",
    "quoteTime": "11.10 a.m.",
    "quoteLast": ", and reached Portsmouth at seven p.m. == seven hours fifty minutes, inclusive of seven changes, as against six changes in previous seasons. Captain Hargreaves was the bold projector of this long-distance coach, and since his retirement from the road none other has had the enterprise sufficient for so great an undertaking.",
    "title": "The Portsmouth Road and Its Tributaries: To-Day and in Days of Old",
    "author": "Harper, Charles G. (Charles George), 1863-1943",
    "gutenbergReference": "39234",
    "hash": "afcbb6a58cf8a461f4e1b653077d8a63bb8f03637b9eeb82fdf7c47647969163"
  },
  {
    "time": "11:10",
    "quoteFirst": "274) was begun at 9 A.M. on July 10th; the filament at first moved but little in a zigzag line, but at 2 P.M. it began rising and continued to do so till 9 P.M.; and this proves that the terminal portion was being more bent downwards. After 9 P.M. on the 10th an opposite movement commenced, and the curved portion began to straighten itself, and this continued till ",
    "quoteTime": "11.10 A.M.",
    "quoteLast": " on the 12th, but was interrupted by some small oscillations and zigzags, showing movement in different directions. After 11.10 A.M. on the 12th this part of the stem, still considerably curved, circumnutated in a conspicuous manner until nearly 3 P.M. on the 13th; but during all this time a downward movement of the filament prevailed, caused by the continued straightening of the stem. By the afternoon of the 13th, the summit, which had originally been deflected more than a right angle from the perpendicular, had grown so nearly straight that the tracing could no longer be continued on the vertical glass.",
    "title": "The Power of Movement in Plants",
    "author": "Darwin, Charles, 1809-1882; Darwin, Francis, Sir, 1848-1925",
    "gutenbergReference": "5605",
    "hash": "d796a037ac30343f89931bf49f08ed97a87c49fb4722070a5215145913443fbe"
  }
]